fastoche/__init__.py
fastoche/__version__.py
fastoche-0.1.0rc1.dist-info/LICENSE.txt
fastoche-0.1.0rc1.dist-info/METADATA
fastoche-0.1.0rc1.dist-info/WHEEL
fastoche-0.1.0rc1.dist-info/top_level.txt
fastoche-0.1.0rc1.dist-info/RECORD
